{
	"handy2": [
		{
			"src": "../img/handy/handy1.webp",
			"title": "BMW 8-serie 2-door coupe grey",
			"year": "2021",
			"price": "$62,000",
			"opt1": "Automatic",
			"opt2": "petrol"
		},
	  {
			"src": "../img/handy/handy2.webp",
			"title": "Chevrolet Camaro 2-door convertible blue",
			"year": "2021",
			"price": "$40,000",
			"opt1": "Convertible",
			"opt2": "Diesel"
		},
	  {
			"src": "../img/handy/handy3.webp",
			"title": "Ferrari LaFerrari 2-door coupe red",
			"year": "2021",
			"price": "$810,000",
			"opt1": "Coupe",
			"opt2": "Diesel"
		},
	  {
			"src": "../img/handy/handy4.webp",
			"title": "Audi A8 4-door sedan silver",
			"year": "2021",
			"price": "$70,000",
			"opt1": "sedan",
			"opt2": "Diesel"
		},
	  {
			"src": "../img/handy/handy5.webp",
			"title": "Mercedes-Benz S-class 2-door coupe silver",
			"year": "2021",
			"price": "$76,000",
			"opt1": "Coupe",
			"opt2": "Diesel"
		}
  ]
}